{
  "source": "api.mangaupdates.com",
  "endpoint": "/series/75057488434",
  "requestBody": null,
  "fetchedAt": "2026-07-08T20:14:20.591Z",
  "responseData": {
    "series_id": 75057488434,
    "title": "50 Ways to Leave a Psychopathic Villain",
    "url": "https://www.mangaupdates.com/series/yhbagqa/50-ways-to-leave-a-psychopathic-villain",
    "associated": [
      {
        "title": "50 Cách Để Hủy Hôn Với Phản Diện Tâm Thần"
      },
      {
        "title": "50 Ways to Break Off an Engagement With a Psychopath Villain"
      },
      {
        "title": "50 Ways to Break Off an Engagement With a Psychopathic Villain"
      },
      {
        "title": "50 Ways to Break Up With a Psychopath"
      },
      {
        "title": "50 Ways to Dump the Psychopathic Mastermind"
      },
      {
        "title": "50 способов расстаться с психопатом"
      },
      {
        "title": "50 วิธีล่มงานแต่งกับไซโคพาธตัวพ่อ"
      },
      {
        "title": "Fifty Ways of Escaping My Engagement to a Psychopathic Mastermind"
      },
      {
        "title": "사이코패스 흑막과 파혼하는 50가지 방법"
      }
    ],
    "description": "The novel Evelyn Florence wakes up in has an 18+ rating for a totally different reason than one would expect. It is all because of the story’s psychopathic villain, Duke Cael Hartheon, who goes on to torture the female lead in unspeakable ways. But a bad drunken night results in Evelyn getting tied up with the literal worst character in the novel. Now forced into an impending marriage, Evelyn will do whatever she can to make Cael sick of her and leave her first. But if only the blood-red duke didn’t turn out to be such a green flag...!\n\n**Original Novel:**    \n[Chapters](https://series.naver.com/novel/detail.series?productNo=12083624), [Volumes](https://series.naver.com/novel/detail.series?productNo=13222459) \n\n**Original Webtoon:**   \n[Naver Webtoon](https://comic.naver.com/webtoon/list?titleId=847615), [Naver Series](https://series.naver.com/comic/detail.series?productNo=13718245)\n\n**Official Translations:**   \n[English](https://www.tappytoon.com/en/book/50-ways-to-leave-a-psychopathic-villain), [Thai](https://www.webtoons.com/th/romantic-fantasy/50-ways-to-leave-a-psychopathic-villain/list?title_no=10529) ",
    "image": {
      "url": {
        "original": "https://cdn.mangaupdates.com/image/i523625.png",
        "thumb": "https://cdn.mangaupdates.com/image/thumb/i523625.png"
      },
      "height": 400,
      "width": 275
    },
    "type": "Manhwa",
    "year": "2026",
    "bayesian_rating": 6.85,
    "rating_votes": 13,
    "genres": [
      {
        "genre": "Comedy"
      },
      {
        "genre": "Fantasy"
      },
      {
        "genre": "Romance"
      },
      {
        "genre": "Shoujo"
      }
    ],
    "categories": [
      {
        "series_id": 75057488434,
        "category": "Drunken Intercourse",
        "votes": 1,
        "votes_plus": 1,
        "votes_minus": 0,
        "added_by": 43706520851
      },
      {
        "series_id": 75057488434,
        "category": "Duke Male Lead",
        "votes": 2,
        "votes_plus": 2,
        "votes_minus": 0,
        "added_by": 4411760110
      },
      {
        "series_id": 75057488434,
        "category": "First-Time Intercourse",
        "votes": 2,
        "votes_plus": 2,
        "votes_minus": 0,
        "added_by": 43706520851
      },
      {
        "series_id": 75057488434,
        "category": "Full Color",
        "votes": 1,
        "votes_plus": 1,
        "votes_minus": 0,
        "added_by": 4411760110
      },
      {
        "series_id": 75057488434,
        "category": "Handsome Male Lead",
        "votes": 2,
        "votes_plus": 2,
        "votes_minus": 0,
        "added_by": 4411760110
      },
      {
        "series_id": 75057488434,
        "category": "Isekai",
        "votes": 0,
        "votes_plus": 0,
        "votes_minus": 0,
        "added_by": 4411760110
      },
      {
        "series_id": 75057488434,
        "category": "Nobility/Aristocracy",
        "votes": 1,
        "votes_plus": 1,
        "votes_minus": 0,
        "added_by": 4411760110
      },
      {
        "series_id": 75057488434,
        "category": "One-Night Stand",
        "votes": 2,
        "votes_plus": 2,
        "votes_minus": 0,
        "added_by": 4411760110
      },
      {
        "series_id": 75057488434,
        "category": "Reincarnated as a Side/Extra/Mob Character",
        "votes": 2,
        "votes_plus": 2,
        "votes_minus": 0,
        "added_by": 4411760110
      },
      {
        "series_id": 75057488434,
        "category": "Reincarnated in a Book World",
        "votes": 1,
        "votes_plus": 1,
        "votes_minus": 0,
        "added_by": 4411760110
      }
    ],
    "latest_chapter": 24,
    "forum_id": 39966172897,
    "status": "23 Chapters (Ongoing)",
    "licensed": true,
    "completed": false,
    "anime": {
      "start": null,
      "end": null
    },
    "related_series": [],
    "authors": [
      {
        "name": "Kim Myung-Ran",
        "author_id": null,
        "url": null,
        "type": "Author"
      },
      {
        "name": "Muji",
        "author_id": null,
        "url": null,
        "type": "Author"
      },
      {
        "name": "SOON",
        "author_id": 15994108682,
        "url": "https://www.mangaupdates.com/author/7cih98q/soon",
        "type": "Artist"
      }
    ],
    "publishers": [
      {
        "publisher_name": "Naver",
        "publisher_id": 21494145162,
        "url": "https://www.mangaupdates.com/publisher/9vh24ju/naver",
        "type": "Original",
        "notes": null
      },
      {
        "publisher_name": "Tappytoon",
        "publisher_id": 44201966230,
        "url": "https://www.mangaupdates.com/publisher/kb0pjfa/tappytoon",
        "type": "English",
        "notes": null
      },
      {
        "publisher_name": "tt studio",
        "publisher_id": 52284228393,
        "url": "https://www.mangaupdates.com/publisher/o0oogtl/tt-studio",
        "type": "Original",
        "notes": null
      }
    ],
    "publications": [
      {
        "publication_name": "Naver Webtoon",
        "publisher_name": "Naver",
        "publisher_id": 21494145162
      },
      {
        "publication_name": "Naver Series",
        "publisher_name": "Naver",
        "publisher_id": 21494145162
      }
    ],
    "recommendations": [],
    "category_recommendations": [
      {
        "series_name": "I Was Doted on After Raising the Final Boss Duke's Nephew",
        "series_url": "https://www.mangaupdates.com/series/zub8gcl/i-was-doted-on-after-raising-the-final-boss-duke-s-nephew",
        "series_id": 78020237253,
        "series_image": {
          "url": {
            "original": "https://cdn.mangaupdates.com/image/i477714.png",
            "thumb": "https://cdn.mangaupdates.com/image/thumb/i477714.png"
          },
          "height": 390,
          "width": 276
        },
        "weight": 20000
      },
      {
        "series_name": "I'll Protect You, Daddy!",
        "series_url": "https://www.mangaupdates.com/series/zj8xn0q/i-ll-protect-you-daddy",
        "series_id": 77351245514,
        "series_image": {
          "url": {
            "original": "https://cdn.mangaupdates.com/image/i526891.png",
            "thumb": "https://cdn.mangaupdates.com/image/thumb/i526891.png"
          },
          "height": 400,
          "width": 266
        },
        "weight": 17321
      },
      {
        "series_name": "Let's Get Married First (Yeon Seo Nah)",
        "series_url": "https://www.mangaupdates.com/series/zkn74k8/let-s-get-married-first-yeon-seo-nah",
        "series_id": 77435668952,
        "series_image": {
          "url": {
            "original": "https://cdn.mangaupdates.com/image/i526968.png",
            "thumb": "https://cdn.mangaupdates.com/image/thumb/i526968.png"
          },
          "height": 400,
          "width": 266
        },
        "weight": 17321
      },
      {
        "series_name": "Viola Tames the Duke",
        "series_url": "https://www.mangaupdates.com/series/zsp0h22/viola-tames-the-duke",
        "series_id": 77922447194,
        "series_image": {
          "url": {
            "original": "https://cdn.mangaupdates.com/image/i436294.jpg",
            "thumb": "https://cdn.mangaupdates.com/image/thumb/i436294.jpg"
          },
          "height": 240,
          "width": 160
        },
        "weight": 17321
      },
      {
        "series_name": "Healing the Duke of Darkness",
        "series_url": "https://www.mangaupdates.com/series/yxermex/healing-the-duke-of-darkness",
        "series_id": 76030786617,
        "series_image": {
          "url": {
            "original": "https://cdn.mangaupdates.com/image/i528777.jpg",
            "thumb": "https://cdn.mangaupdates.com/image/thumb/i528777.jpg"
          },
          "height": 400,
          "width": 280
        },
        "weight": 16837
      }
    ],
    "rank": {
      "position": {
        "week": 398,
        "month": 649,
        "three_months": 411,
        "six_months": 262,
        "year": 602
      },
      "old_position": {
        "week": 498,
        "month": 559,
        "three_months": 172,
        "six_months": 820,
        "year": 2016
      },
      "lists": {
        "reading": 118,
        "wish": 97,
        "complete": 5,
        "unfinished": 1,
        "custom": 64
      }
    },
    "last_updated": {
      "timestamp": 1782668495,
      "as_rfc3339": "2026-06-28T10:41:35-07:00",
      "as_string": "June 28th, 2026 10:41am PDT"
    },
    "admin": {
      "approved": true
    }
  },
  "apiVersion": "v1"
}